make_us_rich/__init__.py
make_us_rich/__main__.py
make_us_rich/cli/__init__.py
make_us_rich/cli/main.py
make_us_rich/cli/runner.py
make_us_rich/cli/utils.py
make_us_rich/client/__init__.py
make_us_rich/client/binance_client.py
make_us_rich/client/minio_client.py
make_us_rich/hooks.py
make_us_rich/interface/__init__.py
make_us_rich/interface/api_request.py
make_us_rich/interface/authentication.py
make_us_rich/interface/database_handler.py
make_us_rich/interface/plots.py
make_us_rich/kedro_config.toml
make_us_rich/pipeline_registry.py
make_us_rich/pipelines/__init__.py
make_us_rich/pipelines/converting/__init__.py
make_us_rich/pipelines/converting/nodes.py
make_us_rich/pipelines/converting/pipeline.py
make_us_rich/pipelines/exporting/__init__.py
make_us_rich/pipelines/exporting/nodes.py
make_us_rich/pipelines/exporting/pipeline.py
make_us_rich/pipelines/fetching/__init__.py
make_us_rich/pipelines/fetching/nodes.py
make_us_rich/pipelines/fetching/pipeline.py
make_us_rich/pipelines/preprocessing/__init__.py
make_us_rich/pipelines/preprocessing/nodes.py
make_us_rich/pipelines/preprocessing/pipeline.py
make_us_rich/pipelines/training/__init__.py
make_us_rich/pipelines/training/crypto_dataset.py
make_us_rich/pipelines/training/dataloader.py
make_us_rich/pipelines/training/model.py
make_us_rich/pipelines/training/nodes.py
make_us_rich/pipelines/training/pipeline.py
make_us_rich/serving/__init__.py
make_us_rich/serving/model.py
make_us_rich/serving/model_loader.py
make_us_rich/settings.py
make_us_rich/utils/__init__.py
make_us_rich/utils/directory_cleaning.py
make_us_rich/utils/load_env.py
make_us_rich/utils/random_string.py
make_us_rich/worker/README.md
make_us_rich/worker/__init__.py
make_us_rich/worker/kedro_task.py
make_us_rich/worker/project_metadata.py
make_us_rich-0.1.1.dist-info/entry_points.txt
make_us_rich-0.1.1.dist-info/LICENSE.txt
make_us_rich-0.1.1.dist-info/WHEEL
make_us_rich-0.1.1.dist-info/METADATA
make_us_rich-0.1.1.dist-info/RECORD
